powerline_k8sstatus/__init__.py
powerline_k8sstatus/segments.py
powerline_k8sstatus-21.2.2.dist-info/LICENSE
powerline_k8sstatus-21.2.2.dist-info/METADATA
powerline_k8sstatus-21.2.2.dist-info/WHEEL
powerline_k8sstatus-21.2.2.dist-info/top_level.txt
powerline_k8sstatus-21.2.2.dist-info/RECORD
