Metadata-Version: 2.1
Name: powerline-k8sstatus
Version: 21.2.2
Summary: A Powerline segment for showing the status of current Kubernetes context
Home-page: https://github.com/imjoseangel/powerline-k8sstatus
Author: Jose Angel Munoz
Author-email: josea.munoz@gmail.com
License: MIT
Keywords: powerline k8s kubernetes status prompt
Platform: UNKNOWN
Classifier: Development Status :: 5 - Production/Stable
Classifier: Environment :: Console
Classifier: Intended Audience :: Developers
Classifier: License :: OSI Approved :: MIT License
Classifier: Programming Language :: Python :: 3
Classifier: Topic :: Terminals
Classifier: Topic :: Utilities
Requires-Dist: kubernetes
